merbe/__init__.py
merbe/core.py
merbe-3.1.0.dist-info/METADATA
merbe-3.1.0.dist-info/WHEEL
merbe-3.1.0.dist-info/top_level.txt
merbe-3.1.0.dist-info/RECORD
