Metadata-Version: 2.4
Name: merbe
Version: 3.1.0
Summary: Educational demonstration of dependency confusion
Home-page: https://github.com/merzouka/dependency-confusion.security/blob/main/malicious/src/merbe
Author: BEKHTI DJALAL
Author-email: d.bekhti@esi-sba.dz
Classifier: Development Status :: 4 - Beta
Classifier: Intended Audience :: Education
Classifier: Programming Language :: Python :: 3
Dynamic: author
Dynamic: author-email
Dynamic: classifier
Dynamic: home-page
Dynamic: summary
